flxtrtwn_objectdb/__init__.py
flxtrtwn_objectdb/database.py
flxtrtwn_objectdb/database_mongodb.py
flxtrtwn_objectdb/py.typed
flxtrtwn_objectdb-0.6.0.dist-info/METADATA
flxtrtwn_objectdb-0.6.0.dist-info/WHEEL
flxtrtwn_objectdb-0.6.0.dist-info/RECORD
