Metadata-Version: 2.4
Name: flxtrtwn-objectdb
Version: 0.6.0
Summary: 
Author: Felix Trautwein
Author-email: mail@felixtrautwein.de
Requires-Python: >=3.10,<4.0
Classifier: Programming Language :: Python :: 3
Classifier: Programming Language :: Python :: 3.10
Classifier: Programming Language :: Python :: 3.11
Classifier: Programming Language :: Python :: 3.12
Classifier: Programming Language :: Python :: 3.13
Classifier: Programming Language :: Python :: 3.14
Requires-Dist: pymongo (>=4.12.1)
